valheim_save_tools_py/__init__.py
valheim_save_tools_py/exceptions.py
valheim_save_tools_py/wrapper.py
valheim_save_tools_py/valheim_save_tools/valheim-save-tools.jar
valheim_save_tools_py-0.2.0.dist-info/licenses/LICENSE
valheim_save_tools_py-0.2.0.dist-info/METADATA
valheim_save_tools_py-0.2.0.dist-info/WHEEL
valheim_save_tools_py-0.2.0.dist-info/top_level.txt
valheim_save_tools_py-0.2.0.dist-info/RECORD
