Metadata-Version: 2.4
Name: valheim-save-tools-py
Version: 0.2.0
Summary: A Pythonic wrapper for Valheim Save Tools - manipulate Valheim save files programmatically
Author-email: Jair Ruiz <jaircoto007@gmail.com>
License: MIT
Project-URL: Homepage, https://github.com/JNikolo/valheim-save-tools-py
Project-URL: Documentation, https://github.com/JNikolo/valheim-save-tools-py#readme
Project-URL: Repository, https://github.com/JNikolo/valheim-save-tools-py.git
Project-URL: Issues, https://github.com/JNikolo/valheim-save-tools-py/issues
Keywords: valheim,save,tools,game,modding,savegame
Classifier: Development Status :: 4 - Beta
Classifier: Intended Audience :: Developers
Classifier: License :: OSI Approved :: MIT License
Classifier: Programming Language :: Python :: 3
Classifier: Programming Language :: Python :: 3.8
Classifier: Programming Language :: Python :: 3.9
Classifier: Programming Language :: Python :: 3.10
Classifier: Programming Language :: Python :: 3.11
Classifier: Programming Language :: Python :: 3.12
Classifier: Topic :: Games/Entertainment
Classifier: Topic :: Software Development :: Libraries :: Python Modules
Classifier: Operating System :: OS Independent
Requires-Python: >=3.8
License-File: LICENSE
Provides-Extra: dev
Requires-Dist: pytest>=7.0.0; extra == "dev"
Requires-Dist: pytest-cov>=4.0.0; extra == "dev"
Dynamic: license-file
